{
  "persons": [
    {
      "name": "Arto Hellas",
      "number": "040-123456",
      "id": 1
    },
    {
      "name": "Ada Lovelace",
      "number": "39-44-5323523",
      "id": 2
    },
    {
      "name": "Dan Abramov",
      "number": "12-43-234345",
      "id": 3
    },
    {
      "name": "Mary Poppendieck",
      "number": "39-23-6423122",
      "id": 4
    },
    {
      "name": "Sami Suonpää",
      "number": "1234",
      "id": 5
    },
    {
      "id": 6
    },
    {
      "id": 7
    },
    {
      "name": "asdlkasl",
      "number": "012334",
      "id": 9
    },
    {
      "name": "oiwejoiqwje",
      "number": "125123",
      "id": 10
    },
    {
      "name": "aksdmalkmsd",
      "number": "12315315123",
      "id": 11
    },
    {
      "name": "ajsdalkml",
      "number": "1231532142",
      "id": 13
    },
    {
      "name": "askdnalksmdl",
      "number": "123124512431",
      "id": 14
    },
    {
      "name": "kqlwemlkq",
      "number": "123",
      "id": 15
    },
    {
      "name": "1lk23mlk21m3",
      "number": "123123",
      "id": 19
    },
    {
      "name": "1lk23k12m3lk1",
      "number": "12lk3m1lk2m31",
      "id": 20
    },
    {
      "name": "k12m3k21m3lk",
      "number": "1lk2m3lk12m3",
      "id": 21
    },
    {
      "name": "1lk2m3l1m3l",
      "number": "123mlk1m321",
      "id": 22
    },
    {
      "name": "1lm2 3l1 3",
      "number": "1lk2m3lk12",
      "id": 23
    },
    {
      "name": "1lk23mlk1m3",
      "number": "1l2m3lk13",
      "id": 24
    },
    {
      "name": "1l23mlk1m3",
      "number": "1lk23m1lk23m",
      "id": 25
    },
    {
      "name": "1lk2m3lk1m",
      "number": "lk12m3lk1m",
      "id": 26
    },
    {
      "name": "123lkm",
      "number": "123öl123",
      "id": 27
    }
  ]
}